{
  "temperatureDewPoint": "Dugpunkt",
  "elev": "Højde",
  "temperatureHeatIndex": "Varmeindeks",
  "relativeHumidity": "Relativ luftfugtighed",
  "neighborhood": "Kvarter",
  "validTimeLocal": "Lokal observationstid",
  "precip1Hour": "Nedbørshastighed",
  "precip24Hour": "Nedbør i dag",
  "pressureAltimeter": "Tryk",
  "solarRadiation": "Solstråling",
  "stationID": "Stations-id",
  "temperature": "Temperatur",
  "uvIndex": "UV-indeks",
  "temperatureWindChill": "Vind Chill",
  "windDirectionCardinal": "Vindretning - kardinal",
  "windGust": "Vindstød",
  "windSpeed": "Vindhastighed",
  "windDirection": "Vindretning - grader",
  "narrative": "Vejroversigt",
  "qpfSnow": "Snemængde",
  "daypart": {
    "expired": "I dag udløb",
    "narrative": "Oversigt over prognosen",
    "precipChance": "Sandsynlighed for nedbør",
    "qpf": "Nedbørsmængde",
    "temperature": "Prognose temperatur",
    "windSpeed": "Gennemsnitlig vind"
  }
}